simplevecdb/__init__.py
simplevecdb/async_core.py
simplevecdb/config.py
simplevecdb/constants.py
simplevecdb/core.py
simplevecdb/logging.py
simplevecdb/types.py
simplevecdb/utils.py
simplevecdb/embeddings/__init__.py
simplevecdb/embeddings/models.py
simplevecdb/embeddings/server.py
simplevecdb/engine/__init__.py
simplevecdb/engine/catalog.py
simplevecdb/engine/quantization.py
simplevecdb/engine/search.py
simplevecdb/engine/usearch_index.py
simplevecdb/integrations/__init__.py
simplevecdb/integrations/langchain.py
simplevecdb/integrations/llamaindex.py
simplevecdb-2.0.0.dist-info/METADATA
simplevecdb-2.0.0.dist-info/WHEEL
simplevecdb-2.0.0.dist-info/entry_points.txt
simplevecdb-2.0.0.dist-info/licenses/LICENSE
simplevecdb-2.0.0.dist-info/RECORD
