Metadata-Version: 2.4
Name: simplevecdb
Version: 2.0.0
Summary: Dead-simple local vector database powered by usearch HNSW.
Author-email: Dayton Dunbar <coderdayton14@gmail.com>
License: MIT
License-File: LICENSE
Requires-Python: >=3.10
Requires-Dist: numpy>=2.0
Requires-Dist: psutil>=5.9.0
Requires-Dist: python-dotenv>=1.2.1
Requires-Dist: usearch>=2.12
Provides-Extra: examples
Requires-Dist: ollama; extra == 'examples'
Provides-Extra: server
Requires-Dist: fastapi>=0.115; extra == 'server'
Requires-Dist: sentence-transformers>=5.0; extra == 'server'
Requires-Dist: uvicorn[standard]>=0.30; extra == 'server'
